LICENSE
pyn2/__init__.py
pyn2/chart.py
pyn2-0.1.0.dist-info/LICENSE
pyn2-0.1.0.dist-info/METADATA
pyn2-0.1.0.dist-info/WHEEL
pyn2-0.1.0.dist-info/RECORD
