Metadata-Version: 2.1
Name: pyn2
Version: 0.1.0
Summary: A python tool for N-squared chart plotting
Home-page: https://github.com/leomariga/pyn2
License: Apache Licence 2.0
Keywords: N2 chart,Visualization,Data Visualization,Charts,Graphs,Python Chart Library,Plotting,Data Analysis,Charting Library,Scientific Computing,System Engineering
Author: Leonardo Mariga
Author-email: leomariga@gmail.com
Requires-Python: >=3.12,<4.0
Classifier: Intended Audience :: Developers
Classifier: Intended Audience :: Science/Research
Classifier: Intended Audience :: System Administrators
Classifier: License :: OSI Approved :: Apache Software License
Classifier: License :: Other/Proprietary License
Classifier: Operating System :: OS Independent
Classifier: Programming Language :: Python :: 3
Classifier: Programming Language :: Python :: 3.12
Classifier: Topic :: Scientific/Engineering :: Visualization
Classifier: Topic :: Software Development :: Libraries :: Python Modules
Requires-Dist: openmdao (>=3.34.2,<4.0.0)
Project-URL: Repository, https://github.com/leomariga/pyn2
